[
	{
		"Id":1,
		"mane":"同仁堂 六味地黄丸 4盒",
		"tits":"滋阴补肾 千年古方 包邮",
		"price1":"￥51.6",
		"price2":"/￥60",
		"img":"img/20160428153800_504.jpg"	
	},
	{
		"Id":2,
		"mane":"同仁堂 六味地黄丸 4盒",
		"tits":"滋阴补肾 千年古方 包邮",
		"price1":"￥51.6",
		"price2":"/￥60",
		"img":"img/20160817180457_22.png"	
	},
	{
		"Id":3,
		"mane":"同仁堂 六味地黄丸 4盒",
		"tits":"滋阴补肾 千年古方 包邮",
		"price1":"￥51.6",
		"price2":"/￥60",
		"img":"img/20160428154024_676.jpg"	
	},
	{
		"Id":4,
		"mane":"同仁堂 六味地黄丸 4盒",
		"tits":"滋阴补肾 千年古方 包邮",
		"price1":"￥51.6",
		"price2":"/￥60",
		"img":"img/20160518150942_223.jpg"	
	},
	{
		"Id":5,
		"mane":"同仁堂 六味地黄丸 4盒",
		"tits":"活血化瘀，消肿止痛",
		"price1":"￥90",
		"price2":"/180",
		"img":"img/20160808155521_217.jpg"	
	},
	{
		"Id":6,
		"mane":"云南三七粉",
		"tits":"活血化瘀，消肿止痛",
		"price1":"￥90",
		"price2":"/180",
		"img":"img/20160726180302_811.jpg"	
	}
	
]
